fs_server/__init__.py
fs_server/config.py
fs_server/serve.py
fs_server/serve_ftp.py
prefab_server/__init__.py
prefab_server/serve.py
tendril_server_prefab-0.1.0.dist-info/DESCRIPTION.rst
tendril_server_prefab-0.1.0.dist-info/METADATA
tendril_server_prefab-0.1.0.dist-info/RECORD
tendril_server_prefab-0.1.0.dist-info/WHEEL
tendril_server_prefab-0.1.0.dist-info/metadata.json
tendril_server_prefab-0.1.0.dist-info/top_level.txt
