Metadata-Version: 2.0
Name: tendril-server-prefab
Version: 0.1.0
Summary: JSON-RPC pre-assembled datasets server using Twisted for Tendril
Home-page: https://github.com/chintal/tendril-server-prefab
Author: Chintalagiri Shashank
Author-email: shashank@chintal.in
License: MIT
Keywords: tendril-server-prefab
Platform: UNKNOWN
Classifier: Development Status :: 4 - Beta
Classifier: License :: OSI Approved :: MIT License
Classifier: Natural Language :: English
Classifier: Programming Language :: Python
Requires-Dist: fastjsonrpc
Requires-Dist: jsonpickle
Requires-Dist: twisted
